{
	"class" : {
		 },
	"instance" : {
		"asyncTask" : "SantiagoBragagnolo 7/27/2015 15:18",
		"execute" : "SantiagoBragagnolo 7/28/2015 12:14",
		"future" : "SantiagoBragagnolo 7/27/2015 17:13",
		"inALocalProcess" : "SantiagoBragagnolo 7/23/2015 14:55",
		"inThisProcess" : "SantiagoBragagnolo 7/23/2015 14:55",
		"isCompatible" : "SantiagoBragagnolo 7/27/2015 17:05",
		"job:" : "SantiagoBragagnolo 7/27/2015 15:13",
		"loopingService" : "SantiagoBragagnolo 7/27/2015 16:35",
		"onServiceFinalization:onFailure:" : "SantiagoBragagnolo 7/28/2015 12:12",
		"onSuccess:onFailure:" : "SantiagoBragagnolo 7/28/2015 12:13",
		"priority" : "SantiagoBragagnolo 3/14/2016 18:02",
		"priority:" : "SantiagoBragagnolo 7/29/2015 14:23",
		"privateCreateTask" : "SantiagoBragagnolo 7/27/2015 17:12",
		"privateRun" : "SantiagoBragagnolo 7/29/2015 14:28",
		"result" : "SantiagoBragagnolo 7/27/2015 17:13",
		"send:" : "SantiagoBragagnolo 7/23/2015 14:54",
		"send:to:" : "SantiagoBragagnolo 7/23/2015 14:51",
		"simpleTask" : "SantiagoBragagnolo 7/27/2015 15:10",
		"start" : "SantiagoBragagnolo 7/28/2015 12:14",
		"to:" : "SantiagoBragagnolo 7/23/2015 14:52",
		"verifyForAsync" : "SantiagoBragagnolo 7/27/2015 15:18",
		"verifyForFuture" : "SantiagoBragagnolo 7/27/2015 14:58",
		"verifyForLoopingService" : "SantiagoBragagnolo 7/27/2015 14:55",
		"verifyForResult" : "SantiagoBragagnolo 7/27/2015 14:59",
		"withArgument:" : "SantiagoBragagnolo 7/29/2015 14:23",
		"withArguments:" : "SantiagoBragagnolo 7/29/2015 14:24" } }
